bleujs/__init__.py
bleujs/api_client/__init__.py
bleujs/api_client/async_client.py
bleujs/api_client/client.py
bleujs/api_client/exceptions.py
bleujs/api_client/models.py
bleujs/cli.py
bleujs/core.py
bleujs/ml.py
bleujs/monitoring.py
bleujs/quantum.py
bleujs/security.py
bleujs/utils.py
bleu_js-1.2.3.dist-info/METADATA
bleu_js-1.2.3.dist-info/WHEEL
bleu_js-1.2.3.dist-info/entry_points.txt
bleu_js-1.2.3.dist-info/RECORD
