Metadata-Version: 2.4
Name: bleu-js
Version: 1.2.3
Summary: Advanced AI and Quantum Computing Framework
License: MIT
Author: Bleujs Team
Author-email: support@helloblue.ai
Requires-Python: >=3.10,<4.0
Classifier: Development Status :: 4 - Beta
Classifier: Intended Audience :: Developers
Classifier: License :: OSI Approved :: MIT License
Classifier: Programming Language :: Python :: 3
Classifier: Programming Language :: Python :: 3.10
Classifier: Programming Language :: Python :: 3.11
Classifier: Programming Language :: Python :: 3.12
Classifier: Programming Language :: Python :: 3.13
Classifier: Programming Language :: Python :: 3.14
Classifier: Topic :: Scientific/Engineering :: Artificial Intelligence
Classifier: Topic :: Scientific/Engineering :: Quantum Computing
Requires-Dist: aiofiles (>=24.1.0,<25.0.0)
Requires-Dist: aiohttp (>=3.12.14,<4.0.0)
Requires-Dist: alembic (==1.13.1)
Requires-Dist: boto3 (>=1.24.0,<2.0.0)
Requires-Dist: cryptography (>=45.0.6,<46.0.0)
Requires-Dist: fastapi (>=0.116.1,<0.117.0)
Requires-Dist: gputil (>=1.4.0,<2.0.0)
Requires-Dist: h11 (==0.16.0)
Requires-Dist: httpx (>=0.28.1,<0.29.0)
Requires-Dist: jinja2 (>=3.1.6,<4.0.0)
Requires-Dist: numpy (>=2.2.6,<3.0.0)
Requires-Dist: opentelemetry-api (>=1.35.0,<2.0.0)
Requires-Dist: opentelemetry-sdk (>=1.35.0,<2.0.0)
Requires-Dist: optuna (>=4.4.0,<5.0.0)
Requires-Dist: pandas (>=2.0.0,<3.0.0)
Requires-Dist: passlib (>=1.7.4,<2.0.0)
Requires-Dist: pennylane (>=0.42.1,<0.43.0)
Requires-Dist: prometheus-client (>=0.23.1,<0.24.0)
Requires-Dist: psutil (>=7.0.0,<8.0.0)
Requires-Dist: psycopg2-binary (==2.9.11)
Requires-Dist: pydantic-settings (>=2.10.1,<3.0.0)
Requires-Dist: pydantic[email] (>=2.7.0,<3.0.0)
Requires-Dist: pyjwt (>=2.10.1,<3.0.0)
Requires-Dist: python-dotenv (>=0.21.0,<0.22.0)
Requires-Dist: python-jose[cryptography] (>=3.5.0,<4.0.0)
Requires-Dist: python-multipart (>=0.0.20,<0.0.21)
Requires-Dist: qiskit (>=2.1.1,<3.0.0)
Requires-Dist: qiskit-aer (>=0.17.1,<0.18.0)
Requires-Dist: qiskit-algorithms (>=0.3.0,<0.4.0)
Requires-Dist: ray (>=2.9.0)
Requires-Dist: redis (>=6.2.0,<7.0.0)
Requires-Dist: requests (>=2.32.4,<3.0.0)
Requires-Dist: scikit-learn (>=1.2.2,<2.0.0)
Requires-Dist: setuptools (>=78.1.1,<79.0.0)
Requires-Dist: shap (>=0.48.0,<0.49.0)
Requires-Dist: sparse (>=0.17.0,<0.18.0)
Requires-Dist: sqlalchemy (==2.0.44)
Requires-Dist: tensorflow (>=2.19.0,<3.0.0)
Requires-Dist: torch (>=2.7.1,<3.0.0)
Requires-Dist: urllib3 (>=2.2.3,<3.0.0)
Requires-Dist: uvicorn (==0.27.1)
Requires-Dist: xgboost (>=3.0.2,<4.0.0)
